<?xml version="1.0"?>
<?xml-stylesheet type="text/xsl" href="../isisxsl.xsl"?>
<isis lang="en">
    <stitle>9 SPEED TRANSMISSIONS EATON RT-8609 SERIES - DISASSEMBLE - SHIFTER HOUSING</stitle>
    <svcsection/>
    <svcproc svcproctype="IDcomponent" graphiccount="9">
        <title>SHIFTER HOUSING</title>
        <para>Refer to
            <hotlnk xrefid="f1302981">Figure 81</hotlnk>.
        </para>
        <figure id="f1302981" figsize="col-wide">
            <graphic id="g1302981" filename="../figg13/g1302981.webp" type="webp"/>
            <caption>Figure 81. Shifter Housing Exploded View</caption>
        </figure>
        <step1>
            <para count="1">Remove the two bolts and remove the tension spring cover from the top of the housing (
                <hotlnk xrefid="f1302982">inset, Figure 82</hotlnk>). Remove the three tension springs installed under
                the cover.
            </para>
            <figure id="f1302982" figsize="col-wide">
                <graphic id="g1302982" filename="../figg13/g1302982.webp" type="webp"/>
                <caption>Figure 82. Remove Tension Spring Cover</caption>
            </figure>
        </step1>
        <step1>
            <para count="1">Tilt the housing and remove the three tension balls installed under the springs (
                <hotlnk xrefid="f1302983">Figure 83</hotlnk>).
            </para>
            <figure id="f1302983" figsize="col-wide">
                <graphic id="g1302983" filename="../figg13/g1302983.webp" type="webp"/>
                <caption>Figure 83. Remove Tension Balls</caption>
            </figure>
        </step1>
        <step1>
            <para count="1">Secure the assembly in a vise with the plunger side up (
                <hotlnk xrefid="f1302984">Figure 84</hotlnk>). Secure on the housing flange (front of the housing will
                be to the right).
            </para>
            <figure id="f1302984" figsize="col-wide">
                <graphic id="g1302984" filename="../figg13/g1302984.webp" type="webp"/>
                <caption>Figure 84. Secure Assembly in Vise</caption>
            </figure>
        </step1>
        <specpara>
            <note>
                <para>Starting with the upper bar, move all bars to the right and out of the housing as detailed in the
                    following instructions. Cut the lockwire and remove the lockscrews from each bar just prior to its
                    removal.
                </para>
            </note>
        </specpara>
        <step1>
            <para count="1">Move the LO-Reverse bar to the right and out of the housing, removing the shift yoke from
                the bar (
                <hotlnk xrefid="f1302985">Figure 85</hotlnk>).
            </para>
            <figure id="f1302985" figsize="col-wide">
                <graphic id="g1302985" filename="../figg13/g1302985.webp" type="webp"/>
                <caption>Figure 85. Move LO-Reverse Bar to Right</caption>
            </figure>
            <specpara>
                <note>
                    <para>During disassembly, lay all parts on a clean bench in the order of removal to facilitate
                        reassembly. Bars not being removed must be kept in the neutral position or interlock parts will
                        lock bars.
                    </para>
                </note>
            </specpara>
        </step1>
        <step1>
            <para count="1">Move the 1st-2nd yoke bar to the right and out of the housing, removing the shift yoke from
                the bar (
                <hotlnk xrefid="f1302986">Figure 86</hotlnk>). As the neutral notch in the bar clears the front web,
                remove the interlock pin from the bore in the neutral notch (inset).
            </para>
            <figure id="f1302986" figsize="col-wide">
                <graphic id="g1302986" filename="../figg13/g1302986.webp" type="webp"/>
                <caption>Figure 86. Move 1st-2nd Yoke Bar to Right</caption>
            </figure>
        </step1>
        <step1>
            <para count="1">Remove the clip and actuating ring from the air valve shaft (
                <hotlnk xrefid="f1302987">inset, Figure 87</hotlnk>). Remove the air valve shaft from the rear web.
            </para>
            <figure id="f1302987" figsize="col-wide">
                <graphic id="g1302987" filename="../figg13/g1302987.webp" type="webp"/>
                <caption>Figure 87. Remove Clip and Actuating Ring From Air Valve Shaft</caption>
            </figure>
        </step1>
        <step1>
            <para count="1">Move the 3rd-4th yoke bar to the right and out of the housing, removing the shift yoke from
                the bar (
                <hotlnk xrefid="f1302988">Figure 88</hotlnk>). As the yoke is removed, remove the two interlock balls
                from the front web (inset).
            </para>
            <figure id="f1302988" figsize="col-wide">
                <graphic id="g1302988" filename="../figg13/g1302988.webp" type="webp"/>
                <caption>Figure 88. Move 3rd-4th Yoke Bar to Right</caption>
            </figure>
        </step1>
        <step1>
            <para count="1">If necessary, remove the plug, spring, and reverse-stop plunger from the LO-Reverse speed
                shift yoke bore (
                <hotlnk xrefid="f1302989">Figure 89</hotlnk>).
            </para>
            <figure id="f1302989" figsize="col-wide">
                <graphic id="g1302989" filename="../figg13/g1302989.webp" type="webp"/>
                <caption>Figure 89. Remove Plug, Spring and Reverse-Stop Plunger</caption>
            </figure>
        </step1>
    </svcproc>
    <table>
        <tgroup cols="3">
            <tbody>
                <row>
                    <entry>
                        <para>
                            <hotlnk document="s13029_32.xml">
                                <con_previous/>
                            </hotlnk>
                        </para>
                    </entry>
                    <entry>
                        <para>
                            <hotlnk document="s13029_34.xml">
                                <con_next/>
                            </hotlnk>
                        </para>
                    </entry>
                    <entry>
                        <para>
                            <hotlnk document="s13029.htm" target="_top">
                                <con_toc/>
                            </hotlnk>
                        </para>
                    </entry>
                </row>
            </tbody>
        </tgroup>
    </table>
</isis>
