<?xml version="1.0"?>
<?xml-stylesheet type="text/xsl" href="../isisxslspanish.xsl"?>
<isis lang="es">
    <stitle>Spanish - Manual de diagn&#243;sticos para motores VT 365 (2002) - DIAGN&#211;STICOS DEL SISTEMA DE CONTROL
        ELECTR&#211;NICO - Ubicaci&#243;n de sensores y activadores - Componentes instalados en el veh&#237;culo
    </stitle>
    <svcman/>
    <svcproc graphiccount="2">
        <title>Componentes instalados en el veh&#237;culo</title>
        <figure id="eg9014" figsize="col-wide">
            <graphic id="f24007" filename="../figeg9/eg9014.webp" type="webp" scalefit="1" scalefitwidth="192px"/>
            <caption>APS / IVS</caption>
        </figure>
        <para>El conjunto de APS / IVS est&#225; encima del pedal del acelerador.</para>
        <figure id="f24007" figsize="col-wide">
            <graphic id="eg9013" filename="../figeg9/eg9013.webp" type="webp" scalefit="1" scalefitwidth="272px"/>
            <calloutgroup>
                <callout1 type="arabic">Sensor de la presi&#243;n barom&#233;trica absoluta (BAP)</callout1>
                <callout1 type="arabic">Sensor de la posici&#243;n del acelerador e interruptor de confirmaci&#243;n de
                    ralent&#237; (APS / IVS)
                </callout1>
            </calloutgroup>
        </figure>
        <para>El BAP est&#225; ubicado en el m&#243;dulo de control del conductor (DCM), cerca de la columna de la
            direcci&#243;n.
        </para>
    </svcproc>
    <table>
        <tgroup cols="3">
            <tbody>
                <row>
                    <entry>
                        <para>
                            <hotlnk document="mges240_139.xml">
                                <con_previous/>
                            </hotlnk>
                        </para>
                    </entry>
                    <entry>
                        <para>
                            <hotlnk document="mges240_141.xml">
                                <con_next/>
                            </hotlnk>
                        </para>
                    </entry>
                    <entry>
                        <para>
                            <hotlnk document="mges240.htm" target="_top">
                                <con_toc/>
                            </hotlnk>
                        </para>
                    </entry>
                </row>
            </tbody>
        </tgroup>
    </table>
</isis>
