<?xml version="1.0"?>
<?xml-stylesheet type="text/xsl" href="../isisxslfrench.xsl"?>
<isis lang="fr">
    <stitle>French - R&#201;SERVOIRS DE CARBURANT &#192; DOUBLE ALIMENTATION ET &#192; DOUBLE RETOUR - D&#201;POSE
    </stitle>
    <svcsection/>
    <svcproc svcproctype="remove" graphiccount="5">
        <title>D&#201;POSE</title>
        <step1>
            <para count="1">Vider le carburant du r&#233;servoir &#224; remplacer dans un contenant propre et le garder
                &#224; l'abri des contaminants.
            </para>
        </step1>
        <specpara>
            <warning>
                <para>Ne pas vider le carburant &#224; proximit&#233; d'une flamme nue ou de chaleur intense. Cela
                    constituerait une pratique dangereuse pouvant entra&#238;ner des blessures ou des dommages mat&#233;riels.
                </para>
            </warning>
        </specpara>
        <step1>
            <para count="1">D&#233;brancher les conduites d'alimentation, de retour et de ventilation du r&#233;servoir
                de carburant (
                <hotlnk xrefid="f1500101">figure 1</hotlnk>,
                <hotlnk xrefid="f1500102">figure 2</hotlnk>
                et
                <hotlnk xrefid="f1500103">figure 3</hotlnk>).
            </para>
        </step1>
        <figure id="f1500101" figsize="col-wide">
            <graphic id="g1500101" filename="../figg15/g1500101.webp" type="webp"/>
            <caption>Figure 1. R&#233;servoirs de carburant des mod&#232;les de s&#233;rie 4000</caption>
        </figure>
        <figure id="f1500102" figsize="col-wide">
            <graphic id="g1500102" filename="../figg15/g1500102.webp" type="webp"/>
            <caption>Figure 2. R&#233;servoirs de carburant des mod&#232;les de s&#233;rie 8100</caption>
        </figure>
        <figure id="f1500103" figsize="col-wide">
            <graphic id="g1500103" filename="../figg15/g1500103.webp" type="webp"/>
            <caption>Figure 3. R&#233;servoirs de carburant des mod&#232;les de s&#233;ries 8100, 9200, 9300 et 9400
            </caption>
        </figure>
        <step1>
            <para count="1">D&#233;brancher les c&#226;bles du capteur du niveau de carburant, le cas
                &#233;ch&#233;ant.
            </para>
        </step1>
        <step1>
            <para count="1">Enlever les contre-&#233;crous des courroies du r&#233;servoir de carburant (
                <hotlnk xrefid="f1500104">figure 4</hotlnk>
                et
                <hotlnk xrefid="f1500105">figure 5</hotlnk>).
            </para>
        </step1>
        <figure id="f1500104" figsize="col-wide">
            <graphic id="g1500104" filename="../figg15/g1500104.webp" type="webp"/>
            <caption>Figure 4. Contre-&#233;crous</caption>
        </figure>
        <figure id="f1500105" figsize="col-wide">
            <graphic id="g1500105" filename="../figg15/g1500105.webp" type="webp"/>
            <caption>Figure 5. Courroies de retenue des r&#233;servoirs de carburant des mod&#232;les de s&#233;ries
                8100, 9200, 9300 et 9400
            </caption>
        </figure>
        <step1>
            <para count="1">Enlever le r&#233;servoir de carburant du support (
                <hotlnk xrefid="f1500104">figure 4</hotlnk>
                et
                <hotlnk xrefid="f1500105">figure 5</hotlnk>).
            </para>
        </step1>
        <step1>
            <para count="1">Retirer les raccords des conduites du r&#233;servoir de carburant et les nettoyer afin de
                les r&#233;installer sur le nouveau r&#233;servoir.
            </para>
        </step1>
        <specpara>
            <note>
                <para>Certains r&#233;servoirs sont dot&#233;s d'un robinet d'arr&#234;t optionnel qui se trouve du c&#244;t&#233;
                    alimentation du r&#233;servoir.
                </para>
            </note>
        </specpara>
        <step1>
            <para count="1">Retirer le capteur du niveau de carburant, le cas &#233;ch&#233;ant.</para>
        </step1>
        <step1>
            <para count="1">
                <emph type="bold">S&#233;rie 4000</emph>
                : Retirer la conduite d'alimentation du r&#233;servoir de carburant.
            </para>
        </step1>
        <step1>
            <para count="1">Inspecter le support et les courroies du r&#233;servoir de carburant pour s'assurer qu'ils
                sont en bon &#233;tat. Remplacer toute pi&#232;ce us&#233;e ou endommag&#233;e.
            </para>
        </step1>
    </svcproc>
    <table>
        <tgroup cols="3">
            <tbody>
                <row>
                    <entry>
                        <para>
                            <hotlnk document="f15001_1.xml">
                                <con_previous/>
                            </hotlnk>
                        </para>
                    </entry>
                    <entry>
                        <para>
                            <hotlnk document="f15001_3.xml">
                                <con_next/>
                            </hotlnk>
                        </para>
                    </entry>
                    <entry>
                        <para>
                            <hotlnk document="f15001.htm" target="_top">
                                <con_toc/>
                            </hotlnk>
                        </para>
                    </entry>
                </row>
            </tbody>
        </tgroup>
    </table>
</isis>
