<?xml version="1.0"?>
<?xml-stylesheet type="text/xsl" href="../isisxsl.xsl"?>
<isis lang="en">
    <stitle>ELECTRICAL SYSTEM TROUBLESHOOTING GUIDE - 9200, 9300, 9400 Models Built After January 1, 1995 - ELECTRICAL
        TROUBLESHOOTING LIGHT SYSTEMS - DESCRIPTION - CAB AND TRAILER LIGHTS SWITCH AND RELAYS WIRING
    </stitle>
    <svcman/>
    <svcproc svcproctype="IDcomponent" graphiccount="0">
        <title>CAB AND TRAILER LIGHTS SWITCH AND RELAYS WIRING</title>
        <para>The cab and trailer lights switch is a switch that is used to flash (momentarily turn OFF) the tractor and
            trailer clearance and tail lights. Thus the truck operator can thank the driver of the vehicle he has just
            passed for flashing his headlights, signaling that it is safe to merge back into the driving lane.
        </para>
    </svcproc>
    <table>
        <tgroup cols="3">
            <tbody>
                <row>
                    <entry>
                        <para>
                            <hotlnk document="s08051_161.xml">
                                <con_previous/>
                            </hotlnk>
                        </para>
                    </entry>
                    <entry>
                        <para>
                            <hotlnk document="s08051_163.xml">
                                <con_next/>
                            </hotlnk>
                        </para>
                    </entry>
                    <entry>
                        <para>
                            <hotlnk document="s08051.htm" target="_top">
                                <con_toc/>
                            </hotlnk>
                        </para>
                    </entry>
                </row>
            </tbody>
        </tgroup>
    </table>
</isis>
