<?xml version="1.0"?>
<?xml-stylesheet type="text/xsl" href="../isisxslfrench.xsl"?>
<isis lang="fr">
    <stitle>French - COMPOSANTS DES FREINS - &#201;PURATEUR D'AIR</stitle>
    <svcsection/>
    <svcsubsec>
        <title>&#201;PURATEUR D'AIR</title>
    </svcsubsec>
    <table>
        <tgroup cols="3">
            <tbody>
                <row>
                    <entry>
                        <para>
                            <hotlnk document="f04002r_113.xml">
                                <con_previous/>
                            </hotlnk>
                        </para>
                    </entry>
                    <entry>
                        <para>
                            <hotlnk document="f04002r_115.xml">
                                <con_next/>
                            </hotlnk>
                        </para>
                    </entry>
                    <entry>
                        <para>
                            <hotlnk document="f04002r.htm" target="_top">
                                <con_toc/>
                            </hotlnk>
                        </para>
                    </entry>
                </row>
            </tbody>
        </tgroup>
    </table>
</isis>
